ttrr/__init__.py
ttrr/damageprob/DamageProbability.py
ttrr/damageprob/__init__.py
ttrr/damageprob/probplot.py
ttrr/functionality/Functionality.py
ttrr/functionality/__init__.py
ttrr/hazard/Cyclone.py
ttrr/hazard/__init__.py
ttrr/loss/__init__.py
ttrr/loss/cost.py
ttrr/plot/__init__.py
ttrr/plot/mapplot.py
ttrr/recovery/__init__.py
ttrr/recovery/recovery.py
ttrr/social/__init__.py
ttrr/social/socialanalysis.py
ttrr/vulnerability/DR.py
ttrr/vulnerability/Fragility.py
ttrr/vulnerability/Vulnerability.py
ttrr/vulnerability/__init__.py
ttrr-0.1.0.dist-info/LICENSE
ttrr-0.1.0.dist-info/METADATA
ttrr-0.1.0.dist-info/WHEEL
ttrr-0.1.0.dist-info/top_level.txt
ttrr-0.1.0.dist-info/RECORD
