Metadata-Version: 2.1
Name: ttrr
Version: 0.1.0
Summary: A short description of your project
Home-page: https://github.com/Swaran66/TCRA_SRN
Author: Your Name
Author-email: Your Name <your_email@example.com>
License: MIT License
Requires-Python: >=3.6
License-File: LICENSE
Requires-Dist: numpy>=1.21.0
